physmet/__init__.py
physmet/_axes.py
physmet/_implementations.py
physmet/_types.py
physmet/axis/__init__.py
physmet/axis/_implementations.py
physmet/axis/_operators.py
physmet/axis/_types.py
physmet/base/__init__.py
physmet/data/__init__.py
physmet/data/_functions.py
physmet/data/_implementations.py
physmet/data/_types.py
physmet/indexer/__init__.py
physmet/indexer/_implementations.py
physmet/indexer/_operators.py
physmet/indexer/_types.py
physmet/measurable/__init__.py
physmet/measurable/_measurement.py
physmet/measured/__init__.py
physmet/measured/_functions.py
physmet/measured/_implementations.py
physmet/measured/_operators.py
physmet/measured/_types.py
physmet/metric/__init__.py
physmet/metric/_definitions.py
physmet/metric/_reference.py
physmet/numeric/__init__.py
physmet/numeric/_operators.py
physmet/numeric/_types.py
physmet/numeric/mixins.py
physmet/quantity/__init__.py
physmet/symbolic/__init__.py
physmet/symbolic/_definitions.py
physmet-0.1.5.dist-info/LICENSE
physmet-0.1.5.dist-info/METADATA
physmet-0.1.5.dist-info/WHEEL
physmet-0.1.5.dist-info/RECORD
